{
  "Default": {
    "bias": -100,
    "human_readable": [
      "sci-fi",
      "I",
      "me",
      "my",
      "we",
      "our",
      "alert",
      "alerting",
      "shared",
      "car",
      "Earth",
      "game",
      "system",
      "everyone",
      "seconds",
      "minutes",
      "hour",
      "day",
      "week",
      "month",
      "Fahrenheit",
      "Celsius",
      "Kelvin"
    ],
    "tokens": {
      "16896": -100,
      "32262": -100,
      "17403": -100,
      "10249": -100,
      "1039": -100,
      "8209": -100,
      "4115": -100,
      "50708": -100,
      "9237": -100,
      "10264": -100,
      "53785": -100,
      "27164": -100,
      "16413": -100,
      "34": -100,
      "36": -100,
      "37": -100,
      "36390": -100,
      "39": -100,
      "40": -100,
      "42": -100,
      "30254": -100,
      "49714": -100,
      "54": -100,
      "11318": -100,
      "56": -100,
      "29250": -100,
      "53827": -100,
      "90692": -100,
      "69": -100,
      "582": -100,
      "76354": -100,
      "72": -100,
      "27720": -100,
      "66": -100,
      "594": -100,
      "82": -100,
      "3154": -100,
      "85": -100,
      "37974": -100,
      "86": -100,
      "11350": -100,
      "6749": -100,
      "10846": -100,
      "80989": -100,
      "2660": -100,
      "16997": -100,
      "24677": -100,
      "5225": -100,
      "94314": -100,
      "7276": -100,
      "1136": -100,
      "2160": -100,
      "69744": -100,
      "9331": -100,
      "1654": -100,
      "84599": -100,
      "4730": -100,
      "8828": -100,
      "6791": -100,
      "84619": -100,
      "7823": -100,
      "655": -100,
      "8852": -100,
      "17053": -100,
      "12457": -100,
      "2220": -100,
      "5804": -100,
      "37037": -100,
      "30382": -100,
      "48300": -100,
      "6321": -100,
      "1718": -100,
      "21176": -100,
      "24765": -100,
      "2749": -100,
      "2254": -100,
      "19159": -100,
      "730": -100,
      "220": -100,
      "29923": -100,
      "752": -100,
      "8948": -100,
      "17659": -100,
      "9983": -100,
      "33024": -100,
      "4868": -100,
      "67332": -100,
      "6918": -100,
      "1799": -100,
      "34568": -100,
      "33545": -100,
      "87818": -100,
      "1803": -100,
      "1292": -100,
      "2320": -100,
      "1809": -100,
      "36631": -100,
      "26904": -100,
      "3868": -100,
      "285": -100,
      "287": -100,
      "3872": -100,
      "288": -100,
      "2849": -100,
      "7462": -100,
      "47910": -100,
      "7981": -100,
      "43824": -100,
      "1330": -100,
      "819": -100,
      "91957": -100,
      "5942": -100,
      "22327": -100,
      "40247": -100,
      "1849": -100,
      "71992": -100,
      "6460": -100,
      "4420": -100,
      "3399": -100,
      "25416": -100,
      "847": -100,
      "2388": -100,
      "6486": -100,
      "29015": -100,
      "33112": -100,
      "348": -100,
      "23902": -100,
      "355": -100,
      "356": -100,
      "358": -100,
      "2408": -100,
      "1899": -100,
      "3951": -100,
      "22385": -100,
      "896": -100,
      "9603": -100,
      "8590": -100,
      "97168": -100,
      "27541": -100,
      "17813": -100,
      "46487": -100,
      "16793": -100,
      "5019": -100,
      "413": -100,
      "925": -100,
      "1440": -100,
      "32673": -100,
      "2471": -100,
      "1449": -100,
      "10159": -100,
      "434": -100,
      "70579": -100,
      "5555": -100,
      "952": -100,
      "5050": -100,
      "40892": -100,
      "9156": -100,
      "969": -100,
      "9676": -100,
      "6094": -100,
      "13778": -100,
      "2003": -100,
      "6100": -100,
      "47575": -100,
      "2010": -100,
      "5083": -100,
      "481": -100,
      "15343": -100,
      "45554": -100,
      "2034": -100,
      "9717": -100,
      "13817": -100,
      "5115": -100,
      "91133": -100
    }
  },
  "Inventory": {
    "bias": -100,
    "human_readable": [
      "empty",
      "low"
    ],
    "tokens": {
      "9441": -100,
      "3522": -100,
      "32858": -100,
      "20968": -100,
      "75": -100,
      "53069": -100,
      "4241": -100,
      "594": -100,
      "3347": -100,
      "65146": -100,
      "1047": -100,
      "3194": -100,
      "24187": -100,
      "220": -100,
      "10303": -100,
      "4287": -100
    }
  },
  "Monetary Transaction": {
    "bias": -100,
    "human_readable": [
      "paid",
      "spent",
      "deducted",
      "sci-fi",
      "twist",
      "trillion",
      "currency",
      "dollar",
      "poetic",
      "withdrawn"
    ],
    "tokens": {
      "7681": -100,
      "7171": -100,
      "51715": -100,
      "9228": -100,
      "1047": -100,
      "1561": -100,
      "21535": -100,
      "34": -100,
      "35": -100,
      "36": -100,
      "40": -100,
      "1578": -100,
      "45": -100,
      "46": -100,
      "52": -100,
      "9789": -100,
      "575": -100,
      "66": -100,
      "67": -100,
      "53827": -100,
      "90692": -100,
      "69": -100,
      "77": -100,
      "594": -100,
      "82": -100,
      "83": -100,
      "37974": -100,
      "15973": -100,
      "92261": -100,
      "2154": -100,
      "7276": -100,
      "1133": -100,
      "6767": -100,
      "1136": -100,
      "3193": -100,
      "63610": -100,
      "44671": -100,
      "1671": -100,
      "32904": -100,
      "654": -100,
      "11413": -100,
      "667": -100,
      "94364": -100,
      "2715": -100,
      "2220": -100,
      "90287": -100,
      "5298": -100,
      "1211": -100,
      "15560": -100,
      "11472": -100,
      "26321": -100,
      "8915": -100,
      "24279": -100,
      "220": -100,
      "7391": -100,
      "11490": -100,
      "5862": -100,
      "77035": -100,
      "5356": -100,
      "1271": -100,
      "5368": -100,
      "9983": -100,
      "1282": -100,
      "6406": -100,
      "3846": -100,
      "267": -100,
      "272": -100,
      "277": -100,
      "36631": -100,
      "285": -100,
      "22816": -100,
      "1825": -100,
      "4384": -100,
      "291": -100,
      "290": -100,
      "3365": -100,
      "805": -100,
      "294": -100,
      "292": -100,
      "297": -100,
      "1317": -100,
      "302": -100,
      "21295": -100,
      "306": -100,
      "1842": -100,
      "308": -100,
      "4412": -100,
      "1348": -100,
      "2378": -100,
      "97099": -100,
      "2388": -100,
      "4451": -100,
      "8041": -100,
      "5999": -100,
      "10610": -100,
      "34678": -100,
      "376": -100,
      "380": -100,
      "14726": -100,
      "85385": -100,
      "908": -100,
      "28050": -100,
      "915": -100,
      "934": -100,
      "70579": -100,
      "7106": -100,
      "6595": -100,
      "965": -100,
      "966": -100,
      "1479": -100,
      "57292": -100,
      "14798": -100,
      "978": -100,
      "47069": -100,
      "481": -100,
      "60903": -100,
      "489": -100,
      "12268": -100,
      "62446": -100,
      "4592": -100,
      "2045": -100
    }
  },
  "Notification": {
    "bias": -100,
    "human_readable": [
      "siren",
      "warning",
      "alert"
    ],
    "tokens": {
      "274": -100,
      "60447": -100,
      "1440": -100,
      "40": -100,
      "554": -100,
      "7466": -100,
      "45": -100,
      "18993": -100,
      "50": -100,
      "12087": -100,
      "4412": -100,
      "32704": -100,
      "29250": -100,
      "3399": -100,
      "969": -100,
      "9676": -100,
      "77": -100,
      "594": -100,
      "82": -100,
      "5083": -100,
      "220": -100,
      "43750": -100,
      "9958": -100,
      "18928": -100,
      "5115": -100,
      "91133": -100,
      "46335": -100
    }
  },
  "Discovery": {
    "bias": -100,
    "human_readable": [
      "name",
      "Earth",
      "["
    ],
    "tokens": {
      "16896": -100,
      "11400": -100,
      "9237": -100,
      "27541": -100,
      "17813": -100,
      "675": -100,
      "36": -100,
      "677": -100,
      "5036": -100,
      "43824": -100,
      "58": -100,
      "829": -100,
      "76354": -100,
      "2509": -100,
      "594": -100,
      "82": -100,
      "220": -100,
      "606": -100,
      "11880": -100,
      "7535": -100,
      "508": -100
    }
  },
  "Environmental Status": {
    "bias": -100,
    "human_readable": [
      "environment",
      "degrees"
    ],
    "tokens": {
      "1570": -100,
      "57063": -100,
      "21737": -100,
      "12348": -100,
      "65119": -100,
      "594": -100,
      "12723": -100,
      "78291": -100,
      "69749": -100,
      "30360": -100,
      "1150": -100,
      "220": -100,
      "4573": -100,
      "23294": -100,
      "59839": -100
    }
  },
  "Freighter Combat": {
    "bias": -100,
    "human_readable": [
      "under",
      "Combat"
    ],
    "tokens": {
      "36192": -100,
      "31009": -100,
      "53274": -100,
      "1862": -100,
      "85643": -100,
      "35982": -100,
      "81391": -100,
      "594": -100,
      "220": -100,
      "22454": -100,
      "61303": -100,
      "8696": -100,
      "16250": -100,
      "7995": -100,
      "1212": -100,
      "25373": -100
    }
  },
  "Missile Launch": {
    "bias": -100,
    "human_readable": [
      "sky",
      "skies",
      "plane",
      "aircraft"
    ],
    "tokens": {
      "3720": -100,
      "34570": -100,
      "10770": -100,
      "4886": -100,
      "11031": -100,
      "1047": -100,
      "24730": -100,
      "1310": -100,
      "288": -100,
      "7712": -100,
      "34": -100,
      "550": -100,
      "40": -100,
      "38057": -100,
      "27819": -100,
      "78891": -100,
      "56": -100,
      "26684": -100,
      "38849": -100,
      "53958": -100,
      "43848": -100,
      "57161": -100,
      "19025": -100,
      "594": -100,
      "15699": -100,
      "12884": -100,
      "82": -100,
      "19290": -100,
      "220": -100,
      "25693": -100,
      "84321": -100,
      "2787": -100,
      "2916": -100,
      "1901": -100,
      "4720": -100,
      "5369": -100,
      "45948": -100
    }
  },
  "Freighter Escape": {
    "bias": -100,
    "human_readable": [
      "sky",
      "skies",
      "plane",
      "aircraft"
    ],
    "tokens": {
      "3720": -100,
      "34570": -100,
      "10770": -100,
      "4886": -100,
      "11031": -100,
      "1047": -100,
      "24730": -100,
      "1310": -100,
      "288": -100,
      "7712": -100,
      "34": -100,
      "550": -100,
      "40": -100,
      "38057": -100,
      "27819": -100,
      "78891": -100,
      "56": -100,
      "26684": -100,
      "38849": -100,
      "53958": -100,
      "43848": -100,
      "57161": -100,
      "19025": -100,
      "594": -100,
      "15699": -100,
      "12884": -100,
      "82": -100,
      "19290": -100,
      "220": -100,
      "25693": -100,
      "84321": -100,
      "2787": -100,
      "2916": -100,
      "1901": -100,
      "4720": -100,
      "5369": -100,
      "45948": -100
    }
  },
  "Missile Destroyed": {
    "bias": -100,
    "human_readable": [
      "sky",
      "skies",
      "plane",
      "aircraft"
    ],
    "tokens": {
      "3720": -100,
      "34570": -100,
      "10770": -100,
      "4886": -100,
      "11031": -100,
      "1047": -100,
      "24730": -100,
      "1310": -100,
      "288": -100,
      "7712": -100,
      "34": -100,
      "550": -100,
      "40": -100,
      "38057": -100,
      "27819": -100,
      "78891": -100,
      "56": -100,
      "26684": -100,
      "38849": -100,
      "53958": -100,
      "43848": -100,
      "57161": -100,
      "19025": -100,
      "594": -100,
      "15699": -100,
      "12884": -100,
      "82": -100,
      "19290": -100,
      "220": -100,
      "25693": -100,
      "84321": -100,
      "2787": -100,
      "2916": -100,
      "1901": -100,
      "4720": -100,
      "5369": -100,
      "45948": -100
    }
  },
  "Personal Combat": {
    "bias": -100,
    "human_readable": [
      "vital",
      "shadow",
      "shadowy",
      "Vital",
      "alers",
      "squad",
      "team",
      "crew",
      "alert"
    ],
    "tokens": {
      "388": -100,
      "14597": -100,
      "647": -100,
      "5115": -100,
      "16265": -100,
      "8590": -100,
      "1808": -100,
      "91133": -100,
      "274": -100,
      "6165": -100,
      "278": -100,
      "1047": -100,
      "51737": -100,
      "922": -100,
      "97052": -100,
      "927": -100,
      "34": -100,
      "2083": -100,
      "33188": -100,
      "12455": -100,
      "11562": -100,
      "4266": -100,
      "432": -100,
      "50": -100,
      "53": -100,
      "2101": -100,
      "54": -100,
      "32952": -100,
      "56": -100,
      "13627": -100,
      "446": -100,
      "31810": -100,
      "29250": -100,
      "21060": -100,
      "59332": -100,
      "452": -100,
      "837": -100,
      "3399": -100,
      "969": -100,
      "27082": -100,
      "42060": -100,
      "9676": -100,
      "34512": -100,
      "594": -100,
      "82": -100,
      "2132": -100,
      "85": -100,
      "43474": -100,
      "9427": -100,
      "88": -100,
      "38617": -100,
      "8915": -100,
      "5083": -100,
      "220": -100,
      "348": -100,
      "7263": -100,
      "38496": -100,
      "4321": -100,
      "42982": -100,
      "1127": -100,
      "55785": -100,
      "9196": -100,
      "7664": -100,
      "23667": -100,
      "31610": -100,
      "379": -100,
      "5757": -100,
      "2174": -100
    }
  },
  "Personal Protection": {
    "bias": -100,
    "human_readable": [
      "guard",
      "%",
      "guardian",
      "our"
    ],
    "tokens": {
      "4": -100,
      "5380": -100,
      "6": -100,
      "6791": -100,
      "1039": -100,
      "78738": -100,
      "276": -100,
      "12952": -100,
      "413": -100,
      "54695": -100,
      "2471": -100,
      "7981": -100,
      "7616": -100,
      "79168": -100,
      "26178": -100,
      "20806": -100,
      "1103": -100,
      "7376": -100,
      "594": -100,
      "82": -100,
      "596": -100,
      "11350": -100,
      "600": -100,
      "220": -100,
      "27238": -100,
      "26098": -100,
      "22002": -100,
      "1018": -100
    }
  },
  "Starship Combat": {
    "bias": -100,
    "human_readable": [
      "aircraft",
      "airborne"
    ],
    "tokens": {
      "9223": -100,
      "3720": -100,
      "16907": -100,
      "84495": -100,
      "10770": -100,
      "30996": -100,
      "1310": -100,
      "7712": -100,
      "288": -100,
      "34": -100,
      "33": -100,
      "78891": -100,
      "64062": -100,
      "38849": -100,
      "53958": -100,
      "43848": -100,
      "57161": -100,
      "594": -100,
      "82": -100,
      "220": -100,
      "25693": -100,
      "3944": -100,
      "4720": -100,
      "15998": -100
    }
  },
  "Starship Movement": {
    "bias": -100,
    "human_readable": [
      "pilot"
    ],
    "tokens": {
      "9184": -100,
      "321": -100,
      "15745": -100,
      "354": -100,
      "3815": -100,
      "40": -100,
      "2412": -100,
      "47": -100,
      "79": -100,
      "594": -100,
      "4726": -100,
      "23958": -100,
      "281": -100,
      "1690": -100,
      "220": -100
    }
  },
  "Radiation Exposure": {
    "bias": -100,
    "human_readable": [
      "our"
    ],
    "tokens": {
      "6791": -100,
      "2471": -100,
      "7981": -100,
      "1039": -100,
      "594": -100,
      "11350": -100,
      "220": -100,
      "413": -100
    }
  },
  "Thinking Deprecated": {
    "bias": -50,
    "human_readable": [
      "wait",
      "alternatively",
      "hmm",
      "but",
      "however",
      "alternative",
      "another",
      "check",
      "double-check",
      "oh",
      "maybe",
      "verify",
      "other",
      "again",
      "now",
      "ah",
      "any"
    ],
    "tokens": {
      "32771": -50,
      "518": -50,
      "1549": -50,
      "3090": -50,
      "5652": -50,
      "1047": -50,
      "7196": -50,
      "33": -50,
      "5158": -50,
      "39": -50,
      "1575": -50,
      "44": -50,
      "97836": -50,
      "12341": -50,
      "49209": -50,
      "30267": -50,
      "3132": -50,
      "15934": -50,
      "65": -50,
      "67": -50,
      "68": -50,
      "1093": -50,
      "71": -50,
      "76": -50,
      "594": -50,
      "82": -50,
      "85613": -50,
      "1655": -50,
      "10877": -50,
      "11908": -50,
      "38024": -50,
      "46223": -50,
      "11409": -50,
      "4764": -50,
      "12446": -50,
      "46761": -50,
      "1199": -50,
      "23215": -50,
      "30385": -50,
      "2739": -50,
      "3767": -50,
      "24765": -50,
      "76995": -50,
      "14019": -50,
      "3783": -50,
      "1735": -50,
      "714": -50,
      "7887": -50,
      "1231": -50,
      "7378": -50,
      "34516": -50,
      "14037": -50,
      "3800": -50,
      "9433": -50,
      "2267": -50,
      "220": -50,
      "1246": -50,
      "11489": -50,
      "5859": -50,
      "29923": -50,
      "49383": -50,
      "4331": -50,
      "3821": -50,
      "34543": -50,
      "1779": -50,
      "9465": -50,
      "3328": -50,
      "9991": -50,
      "6919": -50,
      "264": -50,
      "276": -50,
      "60197": -50,
      "296": -50,
      "297": -50,
      "305": -50,
      "22327": -50,
      "10555": -50,
      "828": -50,
      "11594": -50,
      "333": -50,
      "77647": -50,
      "26450": -50,
      "46936": -50,
      "351": -50,
      "8035": -50,
      "6499": -50,
      "1381": -50,
      "14190": -50,
      "32627": -50,
      "71032": -50,
      "894": -50,
      "7039": -50,
      "39296": -50,
      "4997": -50,
      "3973": -50,
      "2441": -50,
      "17293": -50,
      "21390": -50,
      "3983": -50,
      "85395": -50,
      "1431": -50,
      "8088": -50,
      "16793": -50,
      "36760": -50,
      "43929": -50,
      "10146": -50,
      "8610": -50,
      "423": -50,
      "2985": -50,
      "18358": -50,
      "1466": -50,
      "3004": -50,
      "1990": -50,
      "969": -50,
      "11209": -50,
      "3022": -50,
      "40412": -50,
      "32220": -50,
      "481": -50,
      "7658": -50,
      "41963": -50,
      "2028": -50,
      "58861": -50,
      "6128": -50,
      "1008": -50,
      "1011": -50,
      "75763": -50
    }
  },
  "Thinking": {
    "bias": -50,
    "human_readable": [
      "wait",
      "alternatively"
    ],
    "tokens": {
      "518": -50,
      "9991": -50,
      "6919": -50,
      "3090": -50,
      "1199": -50,
      "49209": -50,
      "828": -50,
      "3132": -50,
      "3783": -50,
      "969": -50,
      "7887": -50,
      "594": -50,
      "82": -50,
      "46936": -50,
      "40412": -50,
      "220": -50,
      "11489": -50,
      "14190": -50,
      "34543": -50,
      "1655": -50,
      "71032": -50,
      "10877": -50
    }
  },
  "Debugging": {
    "bias": -100,
    "human_readable": [
      "mandatory",
      "debug",
      "test",
      "RedBull",
      "gives",
      "you",
      "wings"
    ],
    "tokens": {
      "641": -100,
      "23042": -100,
      "7939": -100,
      "62088": -100,
      "82186": -100,
      "654": -100,
      "782": -100,
      "6033": -100,
      "1426": -100,
      "3731": -100,
      "70423": -100,
      "1944": -100,
      "54808": -100,
      "8349": -100,
      "5150": -100,
      "23841": -100,
      "33": -100,
      "289": -100,
      "38": -100,
      "2342": -100,
      "40": -100,
      "425": -100,
      "44": -100,
      "10033": -100,
      "28081": -100,
      "2610": -100,
      "52": -100,
      "819": -100,
      "54": -100,
      "65": -100,
      "56389": -100,
      "70": -100,
      "52296": -100,
      "48760": -100,
      "594": -100,
      "82": -100,
      "8915": -100,
      "11860": -100,
      "342": -100,
      "86": -100,
      "88": -100,
      "17624": -100,
      "87258": -100,
      "220": -100,
      "7390": -100,
      "2271": -100,
      "74207": -100,
      "5857": -100,
      "1886": -100,
      "6504": -100,
      "617": -100,
      "498": -100,
      "9330": -100,
      "80116": -100,
      "7032": -100,
      "1273": -100,
      "24958": -100,
      "1151": -100
    }
  }
}